<instance version="5" description="" template="sitrep">
	<variant name="default">
		<uniqueid name="pbgid" value="2081106" />
		<group name="sitrep_bag">
			<float name="timeline_extra_duration" value="3" />
			<list name="elements">
				<template_reference name="element" value="sitrep_data\element" List.ItemID="1646848676">
					<string name="custom_label" value="Signals Truck" />
					<string name="type" value="Image" />
					<string name="style" value="ImageWithDropShadow" />
					<file name="image_path" value="icons\sitrep\camp_na\desert_route_hold\desert_route_hold_signals_truck" />
					<group name="dimension">
						<float name="width" value="250" />
						<float name="height" value="250" />
						<enum name="type" value="Pixels" />
					</group>
					<group name="position">
						<template_reference name="world_position" value="basic_data_types\vector3">
							<float name="x" value="40" />
							<float name="y" value="0" />
							<float name="z" value="200" />
						</template_reference>
						<enum name="type" value="WorldPosition" />
					</group>
					<list name="timeline">
						<template_reference name="animated_property" value="sitrep_data\animated_property" List.ItemID="558155668">
							<list name="keyframes">
								<template_reference name="keyframe" value="sitrep_data\double_keyframe" List.ItemID="1200573561">
									<float name="key_time" value="0" />
									<float name="value" value="15" />
									<enum name="interpolation_type" value="Discrete" />
								</template_reference>
							</list>
							<enum name="property" value="Rotate" />
							<float name="repeat_count" value="0" />
						</template_reference>
						<template_reference name="animated_property" value="sitrep_data\animated_property" List.ItemID="189160356">
							<list name="keyframes">
								<template_reference name="keyframe" value="sitrep_data\position_keyframe" List.ItemID="1242896060">
									<float name="key_time" value="0" />
									<group name="value">
										<template_reference name="world_position" value="basic_data_types\vector3">
											<float name="x" value="450" />
											<float name="y" value="20" />
											<float name="z" value="80" />
										</template_reference>
										<enum name="type" value="WorldPosition" />
									</group>
									<enum name="interpolation_type" value="Discrete" />
								</template_reference>
								<template_reference name="keyframe" value="sitrep_data\position_keyframe" List.ItemID="764410046">
									<float name="key_time" value="1" />
									<group name="value">
										<template_reference name="world_position" value="basic_data_types\vector3">
											<float name="x" value="450" />
											<float name="y" value="20" />
											<float name="z" value="80" />
										</template_reference>
										<enum name="type" value="WorldPosition" />
									</group>
									<enum name="interpolation_type" value="Linear" />
								</template_reference>
								<template_reference name="keyframe" value="sitrep_data\position_keyframe" List.ItemID="776859883">
									<float name="key_time" value="2" />
									<group name="value">
										<template_reference name="world_position" value="basic_data_types\vector3">
											<float name="x" value="120" />
											<float name="y" value="20" />
											<float name="z" value="100" />
										</template_reference>
										<enum name="type" value="WorldPosition" />
									</group>
									<enum name="interpolation_type" value="Linear" />
								</template_reference>
							</list>
							<enum name="property" value="Translate" />
							<float name="repeat_count" value="0" />
						</template_reference>
						<template_reference name="animated_property" value="sitrep_data\animated_property" List.ItemID="804298972">
							<list name="keyframes">
								<template_reference name="keyframe" value="sitrep_data\double_keyframe" List.ItemID="845583037">
									<float name="key_time" value="0" />
									<float name="value" value="1" />
									<enum name="interpolation_type" value="Discrete" />
								</template_reference>
								<template_reference name="keyframe" value="sitrep_data\double_keyframe" List.ItemID="1066488651">
									<float name="key_time" value="14" />
									<float name="value" value="1" />
									<enum name="interpolation_type" value="Linear" />
								</template_reference>
								<template_reference name="keyframe" value="sitrep_data\double_keyframe" List.ItemID="1926675981">
									<float name="key_time" value="15" />
									<float name="value" value="0" />
									<enum name="interpolation_type" value="Linear" />
								</template_reference>
							</list>
							<enum name="property" value="Opacity" />
							<float name="repeat_count" value="0" />
						</template_reference>
					</list>
				</template_reference>
				<template_reference name="element" value="sitrep_data\element" List.ItemID="874279134">
					<string name="custom_label" value="Evac Point" />
					<string name="type" value="Image" />
					<string name="style" value="ImageWithDropShadow" />
					<file name="image_path" value="icons\sitrep\friendly_chalk" />
					<group name="dimension">
						<float name="width" value="300" />
						<float name="height" value="300" />
						<enum name="type" value="Pixels" />
					</group>
					<group name="position">
						<template_reference name="world_position" value="basic_data_types\vector3">
							<float name="x" value="-180" />
							<float name="y" value="0" />
							<float name="z" value="130" />
						</template_reference>
						<enum name="type" value="WorldPosition" />
					</group>
					<list name="timeline">
						<template_reference name="animated_property" value="sitrep_data\animated_property" List.ItemID="1434630738">
							<list name="keyframes">
								<template_reference name="keyframe" value="sitrep_data\double_keyframe" List.ItemID="1385637691">
									<float name="key_time" value="0" />
									<float name="value" value="0" />
									<enum name="interpolation_type" value="Discrete" />
								</template_reference>
								<template_reference name="keyframe" value="sitrep_data\double_keyframe" List.ItemID="320545120">
									<float name="key_time" value="34" />
									<float name="value" value="0" />
									<enum name="interpolation_type" value="Linear" />
								</template_reference>
								<template_reference name="keyframe" value="sitrep_data\double_keyframe" List.ItemID="373534466">
									<float name="key_time" value="35" />
									<float name="value" value="1" />
									<enum name="interpolation_type" value="Linear" />
								</template_reference>
							</list>
							<enum name="property" value="Opacity" />
							<float name="repeat_count" value="0" />
						</template_reference>
					</list>
				</template_reference>
				<template_reference name="element" value="sitrep_data\element" List.ItemID="1365832342">
					<string name="custom_label" value="Allied Defenses Forward Barracks" />
					<string name="type" value="Image" />
					<string name="style" value="ImageWithDropShadow" />
					<file name="image_path" value="icons\sitrep\friendly_alliedcross" />
					<group name="dimension">
						<float name="width" value="150" />
						<float name="height" value="150" />
						<enum name="type" value="Pixels" />
					</group>
					<group name="position">
						<template_reference name="world_position" value="basic_data_types\vector3">
							<float name="x" value="-30" />
							<float name="y" value="0" />
							<float name="z" value="110" />
						</template_reference>
						<enum name="type" value="WorldPosition" />
					</group>
					<list name="timeline">
					</list>
				</template_reference>
				<template_reference name="element" value="sitrep_data\element" List.ItemID="866133645">
					<string name="custom_label" value="Defense area 1" />
					<string name="type" value="Image" />
					<string name="style" value="ImageWithDropShadow" />
					<file name="image_path" value="icons\sitrep\friendly_alliedcross" />
					<group name="dimension">
						<float name="width" value="150" />
						<float name="height" value="150" />
						<enum name="type" value="Pixels" />
					</group>
					<group name="position">
						<template_reference name="world_position" value="basic_data_types\vector3">
							<float name="x" value="-100" />
							<float name="y" value="0" />
							<float name="z" value="-20" />
						</template_reference>
						<enum name="type" value="WorldPosition" />
					</group>
					<list name="timeline">
					</list>
				</template_reference>
				<template_reference name="element" value="sitrep_data\element" List.ItemID="1788042660">
					<string name="custom_label" value="Enemy Vanguard 1" />
					<string name="type" value="Image" />
					<string name="style" value="ImageWithDropShadow" />
					<file name="image_path" value="icons\sitrep\enemy_arrow" />
					<group name="dimension">
						<float name="width" value="150" />
						<float name="height" value="150" />
						<enum name="type" value="Pixels" />
					</group>
					<group name="position">
						<template_reference name="world_position" value="basic_data_types\vector3">
							<float name="x" value="-100" />
							<float name="y" value="0" />
							<float name="z" value="-150" />
						</template_reference>
						<enum name="type" value="WorldPosition" />
					</group>
					<list name="timeline">
						<template_reference name="animated_property" value="sitrep_data\animated_property" List.ItemID="69976569">
							<list name="keyframes">
								<template_reference name="keyframe" value="sitrep_data\double_keyframe" List.ItemID="872323522">
									<float name="key_time" value="0" />
									<float name="value" value="180" />
									<enum name="interpolation_type" value="Discrete" />
								</template_reference>
							</list>
							<enum name="property" value="Rotate" />
							<float name="repeat_count" value="0" />
						</template_reference>
						<template_reference name="animated_property" value="sitrep_data\animated_property" List.ItemID="1097803199">
							<list name="keyframes">
								<template_reference name="keyframe" value="sitrep_data\double_keyframe" List.ItemID="1389550801">
									<float name="key_time" value="0" />
									<float name="value" value="0" />
									<enum name="interpolation_type" value="Discrete" />
								</template_reference>
								<template_reference name="keyframe" value="sitrep_data\double_keyframe" List.ItemID="1202991294">
									<float name="key_time" value="7" />
									<float name="value" value="0" />
									<enum name="interpolation_type" value="Linear" />
								</template_reference>
								<template_reference name="keyframe" value="sitrep_data\double_keyframe" List.ItemID="2008295074">
									<float name="key_time" value="8" />
									<float name="value" value="1" />
									<enum name="interpolation_type" value="Linear" />
								</template_reference>
							</list>
							<enum name="property" value="Opacity" />
							<float name="repeat_count" value="0" />
						</template_reference>
						<template_reference name="animated_property" value="sitrep_data\animated_property" List.ItemID="1925630742">
							<list name="keyframes">
								<template_reference name="keyframe" value="sitrep_data\position_keyframe" List.ItemID="1072940508">
									<float name="key_time" value="0" />
									<group name="value">
										<template_reference name="world_position" value="basic_data_types\vector3">
											<float name="x" value="-100" />
											<float name="y" value="0" />
											<float name="z" value="-150" />
										</template_reference>
										<enum name="type" value="WorldPosition" />
									</group>
									<enum name="interpolation_type" value="Discrete" />
								</template_reference>
								<template_reference name="keyframe" value="sitrep_data\position_keyframe" List.ItemID="279065004">
									<float name="key_time" value="7" />
									<group name="value">
										<template_reference name="world_position" value="basic_data_types\vector3">
											<float name="x" value="-100" />
											<float name="y" value="0" />
											<float name="z" value="-150" />
										</template_reference>
										<enum name="type" value="WorldPosition" />
									</group>
									<enum name="interpolation_type" value="Linear" />
								</template_reference>
								<template_reference name="keyframe" value="sitrep_data\position_keyframe" List.ItemID="1704991964">
									<float name="key_time" value="9" />
									<group name="value">
										<template_reference name="world_position" value="basic_data_types\vector3">
											<float name="x" value="-100" />
											<float name="y" value="0" />
											<float name="z" value="-60" />
										</template_reference>
										<enum name="type" value="WorldPosition" />
									</group>
									<enum name="interpolation_type" value="Linear" />
								</template_reference>
							</list>
							<enum name="property" value="Translate" />
							<float name="repeat_count" value="0" />
						</template_reference>
					</list>
				</template_reference>
				<template_reference name="element" value="sitrep_data\element" List.ItemID="891834338">
					<string name="custom_label" value="Main Force" />
					<string name="type" value="Image" />
					<string name="style" value="ImageWithDropShadow" />
					<file name="image_path" value="icons\sitrep\enemy_arrow" />
					<group name="dimension">
						<float name="width" value="300" />
						<float name="height" value="300" />
						<enum name="type" value="Pixels" />
					</group>
					<group name="position">
						<template_reference name="world_position" value="basic_data_types\vector3">
							<float name="x" value="-130" />
							<float name="y" value="0" />
							<float name="z" value="-450" />
						</template_reference>
						<enum name="type" value="WorldPosition" />
					</group>
					<list name="timeline">
						<template_reference name="animated_property" value="sitrep_data\animated_property" List.ItemID="1327258084">
							<list name="keyframes">
								<template_reference name="keyframe" value="sitrep_data\double_keyframe" List.ItemID="246434369">
									<float name="key_time" value="0" />
									<float name="value" value="160" />
									<enum name="interpolation_type" value="Discrete" />
								</template_reference>
							</list>
							<enum name="property" value="Rotate" />
							<float name="repeat_count" value="0" />
						</template_reference>
						<template_reference name="animated_property" value="sitrep_data\animated_property" List.ItemID="683389864">
							<list name="keyframes">
								<template_reference name="keyframe" value="sitrep_data\double_keyframe" List.ItemID="717998746">
									<float name="key_time" value="0" />
									<float name="value" value="0" />
									<enum name="interpolation_type" value="Discrete" />
								</template_reference>
								<template_reference name="keyframe" value="sitrep_data\double_keyframe" List.ItemID="1034101385">
									<float name="key_time" value="25" />
									<float name="value" value="0" />
									<enum name="interpolation_type" value="Linear" />
								</template_reference>
								<template_reference name="keyframe" value="sitrep_data\double_keyframe" List.ItemID="1191843686">
									<float name="key_time" value="26" />
									<float name="value" value="1" />
									<enum name="interpolation_type" value="Linear" />
								</template_reference>
							</list>
							<enum name="property" value="Opacity" />
							<float name="repeat_count" value="0" />
						</template_reference>
						<template_reference name="animated_property" value="sitrep_data\animated_property" List.ItemID="71732326">
							<list name="keyframes">
								<template_reference name="keyframe" value="sitrep_data\position_keyframe" List.ItemID="1007501389">
									<float name="key_time" value="0" />
									<group name="value">
										<template_reference name="world_position" value="basic_data_types\vector3">
											<float name="x" value="-130" />
											<float name="y" value="0" />
											<float name="z" value="-450" />
										</template_reference>
										<enum name="type" value="WorldPosition" />
									</group>
									<enum name="interpolation_type" value="Discrete" />
								</template_reference>
								<template_reference name="keyframe" value="sitrep_data\position_keyframe" List.ItemID="2109478600">
									<float name="key_time" value="26" />
									<group name="value">
										<template_reference name="world_position" value="basic_data_types\vector3">
											<float name="x" value="-130" />
											<float name="y" value="0" />
											<float name="z" value="-450" />
										</template_reference>
										<enum name="type" value="WorldPosition" />
									</group>
									<enum name="interpolation_type" value="Linear" />
								</template_reference>
								<template_reference name="keyframe" value="sitrep_data\position_keyframe" List.ItemID="325203719">
									<float name="key_time" value="28" />
									<group name="value">
										<template_reference name="world_position" value="basic_data_types\vector3">
											<float name="x" value="-60" />
											<float name="y" value="0" />
											<float name="z" value="-160" />
										</template_reference>
										<enum name="type" value="WorldPosition" />
									</group>
									<enum name="interpolation_type" value="Linear" />
								</template_reference>
							</list>
							<enum name="property" value="Translate" />
							<float name="repeat_count" value="0" />
						</template_reference>
					</list>
				</template_reference>
				<template_reference name="element" value="sitrep_data\element" List.ItemID="545888306">
					<string name="custom_label" value="Main Force Picture" />
					<string name="type" value="Image" />
					<string name="style" value="ImageWithDropShadow" />
					<file name="image_path" value="icons\sitrep\camp_na\desert_route_hold\desert_route_hold_main_enemy_force" />
					<group name="dimension">
						<float name="width" value="250" />
						<float name="height" value="250" />
						<enum name="type" value="Pixels" />
					</group>
					<group name="position">
						<template_reference name="world_position" value="basic_data_types\vector3">
							<float name="x" value="-400" />
							<float name="y" value="0" />
							<float name="z" value="-150" />
						</template_reference>
						<enum name="type" value="WorldPosition" />
					</group>
					<list name="timeline">
						<template_reference name="animated_property" value="sitrep_data\animated_property" List.ItemID="678349810">
							<list name="keyframes">
								<template_reference name="keyframe" value="sitrep_data\double_keyframe" List.ItemID="105670843">
									<float name="key_time" value="0" />
									<float name="value" value="10" />
									<enum name="interpolation_type" value="Discrete" />
								</template_reference>
							</list>
							<enum name="property" value="Rotate" />
							<float name="repeat_count" value="0" />
						</template_reference>
						<template_reference name="animated_property" value="sitrep_data\animated_property" List.ItemID="2050437429">
							<list name="keyframes">
								<template_reference name="keyframe" value="sitrep_data\double_keyframe" List.ItemID="1945227498">
									<float name="key_time" value="0" />
									<float name="value" value="0" />
									<enum name="interpolation_type" value="Discrete" />
								</template_reference>
								<template_reference name="keyframe" value="sitrep_data\double_keyframe" List.ItemID="1464996493">
									<float name="key_time" value="25" />
									<float name="value" value="0" />
									<enum name="interpolation_type" value="Linear" />
								</template_reference>
								<template_reference name="keyframe" value="sitrep_data\double_keyframe" List.ItemID="1962422212">
									<float name="key_time" value="26" />
									<float name="value" value="1" />
									<enum name="interpolation_type" value="Linear" />
								</template_reference>
							</list>
							<enum name="property" value="Opacity" />
							<float name="repeat_count" value="0" />
						</template_reference>
						<template_reference name="animated_property" value="sitrep_data\animated_property" List.ItemID="442655195">
							<list name="keyframes">
								<template_reference name="keyframe" value="sitrep_data\position_keyframe" List.ItemID="5926055">
									<float name="key_time" value="0" />
									<group name="value">
										<template_reference name="world_position" value="basic_data_types\vector3">
											<float name="x" value="-400" />
											<float name="y" value="0" />
											<float name="z" value="-150" />
										</template_reference>
										<enum name="type" value="WorldPosition" />
									</group>
									<enum name="interpolation_type" value="Discrete" />
								</template_reference>
								<template_reference name="keyframe" value="sitrep_data\position_keyframe" List.ItemID="888790345">
									<float name="key_time" value="26" />
									<group name="value">
										<template_reference name="world_position" value="basic_data_types\vector3">
											<float name="x" value="-400" />
											<float name="y" value="0" />
											<float name="z" value="-150" />
										</template_reference>
										<enum name="type" value="WorldPosition" />
									</group>
									<enum name="interpolation_type" value="Linear" />
								</template_reference>
								<template_reference name="keyframe" value="sitrep_data\position_keyframe" List.ItemID="1005545364">
									<float name="key_time" value="28" />
									<group name="value">
										<template_reference name="world_position" value="basic_data_types\vector3">
											<float name="x" value="-170" />
											<float name="y" value="0" />
											<float name="z" value="-150" />
										</template_reference>
										<enum name="type" value="WorldPosition" />
									</group>
									<enum name="interpolation_type" value="Linear" />
								</template_reference>
							</list>
							<enum name="property" value="Translate" />
							<float name="repeat_count" value="0" />
						</template_reference>
					</list>
				</template_reference>
				<template_reference name="element" value="sitrep_data\element" List.ItemID="883743698">
					<string name="custom_label" value="Enemy Vanguard 2" />
					<string name="type" value="Image" />
					<string name="style" value="ImageWithDropShadow" />
					<file name="image_path" value="icons\sitrep\enemy_arrow" />
					<group name="dimension">
						<float name="width" value="150" />
						<float name="height" value="150" />
						<enum name="type" value="Pixels" />
					</group>
					<group name="position">
						<template_reference name="world_position" value="basic_data_types\vector3">
							<float name="x" value="120" />
							<float name="y" value="0" />
							<float name="z" value="-130" />
						</template_reference>
						<enum name="type" value="WorldPosition" />
					</group>
					<list name="timeline">
						<template_reference name="animated_property" value="sitrep_data\animated_property" List.ItemID="883483771">
							<list name="keyframes">
								<template_reference name="keyframe" value="sitrep_data\double_keyframe" List.ItemID="177283555">
									<float name="key_time" value="0" />
									<float name="value" value="180" />
									<enum name="interpolation_type" value="Discrete" />
								</template_reference>
							</list>
							<enum name="property" value="Rotate" />
							<float name="repeat_count" value="0" />
						</template_reference>
						<template_reference name="animated_property" value="sitrep_data\animated_property" List.ItemID="301992222">
							<list name="keyframes">
								<template_reference name="keyframe" value="sitrep_data\double_keyframe" List.ItemID="1154103344">
									<float name="key_time" value="0" />
									<float name="value" value="0" />
									<enum name="interpolation_type" value="Discrete" />
								</template_reference>
								<template_reference name="keyframe" value="sitrep_data\double_keyframe" List.ItemID="1331498875">
									<float name="key_time" value="7" />
									<float name="value" value="0" />
									<enum name="interpolation_type" value="Linear" />
								</template_reference>
								<template_reference name="keyframe" value="sitrep_data\double_keyframe" List.ItemID="1856883092">
									<float name="key_time" value="8" />
									<float name="value" value="1" />
									<enum name="interpolation_type" value="Linear" />
								</template_reference>
							</list>
							<enum name="property" value="Opacity" />
							<float name="repeat_count" value="0" />
						</template_reference>
						<template_reference name="animated_property" value="sitrep_data\animated_property" List.ItemID="272219682">
							<list name="keyframes">
								<template_reference name="keyframe" value="sitrep_data\position_keyframe" List.ItemID="1037536010">
									<float name="key_time" value="0" />
									<group name="value">
										<template_reference name="world_position" value="basic_data_types\vector3">
											<float name="x" value="120" />
											<float name="y" value="0" />
											<float name="z" value="-130" />
										</template_reference>
										<enum name="type" value="WorldPosition" />
									</group>
									<enum name="interpolation_type" value="Discrete" />
								</template_reference>
								<template_reference name="keyframe" value="sitrep_data\position_keyframe" List.ItemID="1393195511">
									<float name="key_time" value="7" />
									<group name="value">
										<template_reference name="world_position" value="basic_data_types\vector3">
											<float name="x" value="120" />
											<float name="y" value="0" />
											<float name="z" value="-130" />
										</template_reference>
										<enum name="type" value="WorldPosition" />
									</group>
									<enum name="interpolation_type" value="Linear" />
								</template_reference>
								<template_reference name="keyframe" value="sitrep_data\position_keyframe" List.ItemID="1318742281">
									<float name="key_time" value="9" />
									<group name="value">
										<template_reference name="world_position" value="basic_data_types\vector3">
											<float name="x" value="120" />
											<float name="y" value="0" />
											<float name="z" value="-40" />
										</template_reference>
										<enum name="type" value="WorldPosition" />
									</group>
									<enum name="interpolation_type" value="Linear" />
								</template_reference>
							</list>
							<enum name="property" value="Translate" />
							<float name="repeat_count" value="0" />
						</template_reference>
					</list>
				</template_reference>
				<template_reference name="element" value="sitrep_data\element" List.ItemID="15208864">
					<string name="custom_label" value="Enemy Vanguard 3" />
					<string name="type" value="Image" />
					<string name="style" value="ImageWithDropShadow" />
					<file name="image_path" value="icons\sitrep\enemy_arrow" />
					<group name="dimension">
						<float name="width" value="150" />
						<float name="height" value="150" />
						<enum name="type" value="Pixels" />
					</group>
					<group name="position">
						<template_reference name="world_position" value="basic_data_types\vector3">
							<float name="x" value="120" />
							<float name="y" value="0" />
							<float name="z" value="-400" />
						</template_reference>
						<enum name="type" value="WorldPosition" />
					</group>
					<list name="timeline">
						<template_reference name="animated_property" value="sitrep_data\animated_property" List.ItemID="687203635">
							<list name="keyframes">
								<template_reference name="keyframe" value="sitrep_data\double_keyframe" List.ItemID="1786033870">
									<float name="key_time" value="0" />
									<float name="value" value="200" />
									<enum name="interpolation_type" value="Discrete" />
								</template_reference>
							</list>
							<enum name="property" value="Rotate" />
							<float name="repeat_count" value="0" />
						</template_reference>
						<template_reference name="animated_property" value="sitrep_data\animated_property" List.ItemID="1496528067">
							<list name="keyframes">
								<template_reference name="keyframe" value="sitrep_data\double_keyframe" List.ItemID="796157076">
									<float name="key_time" value="0" />
									<float name="value" value="0" />
									<enum name="interpolation_type" value="Discrete" />
								</template_reference>
								<template_reference name="keyframe" value="sitrep_data\double_keyframe" List.ItemID="357063085">
									<float name="key_time" value="7" />
									<float name="value" value="0" />
									<enum name="interpolation_type" value="Linear" />
								</template_reference>
								<template_reference name="keyframe" value="sitrep_data\double_keyframe" List.ItemID="486356749">
									<float name="key_time" value="8" />
									<float name="value" value="1" />
									<enum name="interpolation_type" value="Linear" />
								</template_reference>
							</list>
							<enum name="property" value="Opacity" />
							<float name="repeat_count" value="0" />
						</template_reference>
						<template_reference name="animated_property" value="sitrep_data\animated_property" List.ItemID="1045287222">
							<list name="keyframes">
								<template_reference name="keyframe" value="sitrep_data\position_keyframe" List.ItemID="1060811210">
									<float name="key_time" value="0" />
									<group name="value">
										<template_reference name="world_position" value="basic_data_types\vector3">
											<float name="x" value="120" />
											<float name="y" value="0" />
											<float name="z" value="-400" />
										</template_reference>
										<enum name="type" value="WorldPosition" />
									</group>
									<enum name="interpolation_type" value="Discrete" />
								</template_reference>
								<template_reference name="keyframe" value="sitrep_data\position_keyframe" List.ItemID="171215249">
									<float name="key_time" value="7" />
									<group name="value">
										<template_reference name="world_position" value="basic_data_types\vector3">
											<float name="x" value="120" />
											<float name="y" value="0" />
											<float name="z" value="-400" />
										</template_reference>
										<enum name="type" value="WorldPosition" />
									</group>
									<enum name="interpolation_type" value="Linear" />
								</template_reference>
								<template_reference name="keyframe" value="sitrep_data\position_keyframe" List.ItemID="1872599456">
									<float name="key_time" value="9" />
									<group name="value">
										<template_reference name="world_position" value="basic_data_types\vector3">
											<float name="x" value="40" />
											<float name="y" value="0" />
											<float name="z" value="-220" />
										</template_reference>
										<enum name="type" value="WorldPosition" />
									</group>
									<enum name="interpolation_type" value="Linear" />
								</template_reference>
							</list>
							<enum name="property" value="Translate" />
							<float name="repeat_count" value="0" />
						</template_reference>
					</list>
				</template_reference>
				<template_reference name="element" value="sitrep_data\element" List.ItemID="1454866284">
					<string name="custom_label" value="Signals Vehicle 1" />
					<string name="type" value="Image" />
					<string name="style" value="ImageWithDropShadow" />
					<file name="image_path" value="icons\sitrep\primary_objective" />
					<group name="dimension">
						<float name="width" value="100" />
						<float name="height" value="100" />
						<enum name="type" value="Pixels" />
					</group>
					<group name="position">
						<template_reference name="world_position" value="basic_data_types\vector3">
							<float name="x" value="-100" />
							<float name="y" value="0" />
							<float name="z" value="0" />
						</template_reference>
						<enum name="type" value="WorldPosition" />
					</group>
					<list name="timeline">
						<template_reference name="animated_property" value="sitrep_data\animated_property" List.ItemID="1013467707">
							<list name="keyframes">
								<template_reference name="keyframe" value="sitrep_data\position_keyframe" List.ItemID="715102152">
									<float name="key_time" value="0" />
									<group name="value">
										<template_reference name="world_position" value="basic_data_types\vector3">
											<float name="x" value="-100" />
											<float name="y" value="0" />
											<float name="z" value="0" />
										</template_reference>
										<enum name="type" value="WorldPosition" />
									</group>
									<enum name="interpolation_type" value="Discrete" />
								</template_reference>
								<template_reference name="keyframe" value="sitrep_data\position_keyframe" List.ItemID="612769334">
									<float name="key_time" value="35" />
									<group name="value">
										<template_reference name="world_position" value="basic_data_types\vector3">
											<float name="x" value="-100" />
											<float name="y" value="0" />
											<float name="z" value="0" />
										</template_reference>
										<enum name="type" value="WorldPosition" />
									</group>
									<enum name="interpolation_type" value="Linear" />
								</template_reference>
								<template_reference name="keyframe" value="sitrep_data\position_keyframe" List.ItemID="1326235381">
									<float name="key_time" value="38" />
									<group name="value">
										<template_reference name="world_position" value="basic_data_types\vector3">
											<float name="x" value="-180" />
											<float name="y" value="0" />
											<float name="z" value="130" />
										</template_reference>
										<enum name="type" value="WorldPosition" />
									</group>
									<enum name="interpolation_type" value="Linear" />
								</template_reference>
							</list>
							<enum name="property" value="Translate" />
							<float name="repeat_count" value="0" />
						</template_reference>
					</list>
				</template_reference>
				<template_reference name="element" value="sitrep_data\element" List.ItemID="1415150293">
					<string name="custom_label" value="Signals Vehicle 1 Cross" />
					<string name="type" value="Image" />
					<string name="style" value="ImageWithDropShadow" />
					<file name="image_path" value="icons\sitrep\enemy_cross" />
					<group name="dimension">
						<float name="width" value="100" />
						<float name="height" value="100" />
						<enum name="type" value="Pixels" />
					</group>
					<group name="position">
						<template_reference name="world_position" value="basic_data_types\vector3">
							<float name="x" value="-100" />
							<float name="y" value="0" />
							<float name="z" value="0" />
						</template_reference>
						<enum name="type" value="WorldPosition" />
					</group>
					<list name="timeline">
						<template_reference name="animated_property" value="sitrep_data\animated_property" List.ItemID="835434427">
							<list name="keyframes">
								<template_reference name="keyframe" value="sitrep_data\double_keyframe" List.ItemID="731760429">
									<float name="key_time" value="0" />
									<float name="value" value="0" />
									<enum name="interpolation_type" value="Discrete" />
								</template_reference>
								<template_reference name="keyframe" value="sitrep_data\double_keyframe" List.ItemID="1245187592">
									<float name="key_time" value="13" />
									<float name="value" value="0" />
									<enum name="interpolation_type" value="Linear" />
								</template_reference>
								<template_reference name="keyframe" value="sitrep_data\double_keyframe" List.ItemID="1995911565">
									<float name="key_time" value="14" />
									<float name="value" value="1" />
									<enum name="interpolation_type" value="Linear" />
								</template_reference>
								<template_reference name="keyframe" value="sitrep_data\double_keyframe" List.ItemID="544435870">
									<float name="key_time" value="16" />
									<float name="value" value="1" />
									<enum name="interpolation_type" value="Linear" />
								</template_reference>
								<template_reference name="keyframe" value="sitrep_data\double_keyframe" List.ItemID="126246163">
									<float name="key_time" value="17" />
									<float name="value" value="0" />
									<enum name="interpolation_type" value="Linear" />
								</template_reference>
							</list>
							<enum name="property" value="Opacity" />
							<float name="repeat_count" value="0" />
						</template_reference>
					</list>
				</template_reference>
				<template_reference name="element" value="sitrep_data\element" List.ItemID="1316919918">
					<string name="custom_label" value="Signals Vehicle 1 Revival" />
					<string name="type" value="Image" />
					<string name="style" value="ImageWithDropShadow" />
					<file name="image_path" value="icons\sitrep\friendly_chalk" />
					<group name="dimension">
						<float name="width" value="100" />
						<float name="height" value="100" />
						<enum name="type" value="Pixels" />
					</group>
					<group name="position">
						<template_reference name="world_position" value="basic_data_types\vector3">
							<float name="x" value="-100" />
							<float name="y" value="0" />
							<float name="z" value="0" />
						</template_reference>
						<enum name="type" value="WorldPosition" />
					</group>
					<list name="timeline">
						<template_reference name="animated_property" value="sitrep_data\animated_property" List.ItemID="693014509">
							<list name="keyframes">
								<template_reference name="keyframe" value="sitrep_data\double_keyframe" List.ItemID="1423642738">
									<float name="key_time" value="0" />
									<float name="value" value="0" />
									<enum name="interpolation_type" value="Discrete" />
								</template_reference>
								<template_reference name="keyframe" value="sitrep_data\double_keyframe" List.ItemID="2142825048">
									<float name="key_time" value="17" />
									<float name="value" value="0" />
									<enum name="interpolation_type" value="Linear" />
								</template_reference>
								<template_reference name="keyframe" value="sitrep_data\double_keyframe" List.ItemID="1637534342">
									<float name="key_time" value="18" />
									<float name="value" value="1" />
									<enum name="interpolation_type" value="Linear" />
								</template_reference>
							</list>
							<enum name="property" value="Opacity" />
							<float name="repeat_count" value="0" />
						</template_reference>
						<template_reference name="animated_property" value="sitrep_data\animated_property" List.ItemID="427129349">
							<list name="keyframes">
								<template_reference name="keyframe" value="sitrep_data\position_keyframe" List.ItemID="1915467994">
									<float name="key_time" value="0" />
									<group name="value">
										<template_reference name="world_position" value="basic_data_types\vector3">
											<float name="x" value="-100" />
											<float name="y" value="0" />
											<float name="z" value="0" />
										</template_reference>
										<enum name="type" value="WorldPosition" />
									</group>
									<enum name="interpolation_type" value="Discrete" />
								</template_reference>
								<template_reference name="keyframe" value="sitrep_data\position_keyframe" List.ItemID="825583517">
									<float name="key_time" value="35" />
									<group name="value">
										<template_reference name="world_position" value="basic_data_types\vector3">
											<float name="x" value="-100" />
											<float name="y" value="0" />
											<float name="z" value="0" />
										</template_reference>
										<enum name="type" value="WorldPosition" />
									</group>
									<enum name="interpolation_type" value="Linear" />
								</template_reference>
								<template_reference name="keyframe" value="sitrep_data\position_keyframe" List.ItemID="1748347187">
									<float name="key_time" value="38" />
									<group name="value">
										<template_reference name="world_position" value="basic_data_types\vector3">
											<float name="x" value="-180" />
											<float name="y" value="0" />
											<float name="z" value="130" />
										</template_reference>
										<enum name="type" value="WorldPosition" />
									</group>
									<enum name="interpolation_type" value="Linear" />
								</template_reference>
							</list>
							<enum name="property" value="Translate" />
							<float name="repeat_count" value="0" />
						</template_reference>
					</list>
				</template_reference>
				<template_reference name="element" value="sitrep_data\element" List.ItemID="264503844">
					<string name="custom_label" value="Defense area 2" />
					<string name="type" value="Image" />
					<string name="style" value="ImageWithDropShadow" />
					<file name="image_path" value="icons\sitrep\friendly_alliedcross" />
					<group name="dimension">
						<float name="width" value="150" />
						<float name="height" value="150" />
						<enum name="type" value="Pixels" />
					</group>
					<group name="position">
						<template_reference name="world_position" value="basic_data_types\vector3">
							<float name="x" value="120" />
							<float name="y" value="0" />
							<float name="z" value="0" />
						</template_reference>
						<enum name="type" value="WorldPosition" />
					</group>
					<list name="timeline">
					</list>
				</template_reference>
				<template_reference name="element" value="sitrep_data\element" List.ItemID="1933134732">
					<string name="custom_label" value="Signals Vehicle 2" />
					<string name="type" value="Image" />
					<string name="style" value="ImageWithDropShadow" />
					<file name="image_path" value="icons\sitrep\primary_objective" />
					<group name="dimension">
						<float name="width" value="100" />
						<float name="height" value="100" />
						<enum name="type" value="Pixels" />
					</group>
					<group name="position">
						<template_reference name="world_position" value="basic_data_types\vector3">
							<float name="x" value="120" />
							<float name="y" value="0" />
							<float name="z" value="20" />
						</template_reference>
						<enum name="type" value="WorldPosition" />
					</group>
					<list name="timeline">
						<template_reference name="animated_property" value="sitrep_data\animated_property" List.ItemID="1865703825">
							<list name="keyframes">
								<template_reference name="keyframe" value="sitrep_data\position_keyframe" List.ItemID="58051926">
									<float name="key_time" value="0" />
									<group name="value">
										<template_reference name="world_position" value="basic_data_types\vector3">
											<float name="x" value="120" />
											<float name="y" value="0" />
											<float name="z" value="20" />
										</template_reference>
										<enum name="type" value="WorldPosition" />
									</group>
									<enum name="interpolation_type" value="Discrete" />
								</template_reference>
								<template_reference name="keyframe" value="sitrep_data\position_keyframe" List.ItemID="1493591849">
									<float name="key_time" value="35" />
									<group name="value">
										<template_reference name="world_position" value="basic_data_types\vector3">
											<float name="x" value="120" />
											<float name="y" value="0" />
											<float name="z" value="20" />
										</template_reference>
										<enum name="type" value="WorldPosition" />
									</group>
									<enum name="interpolation_type" value="Linear" />
								</template_reference>
								<template_reference name="keyframe" value="sitrep_data\position_keyframe" List.ItemID="970759064">
									<float name="key_time" value="38" />
									<group name="value">
										<template_reference name="world_position" value="basic_data_types\vector3">
											<float name="x" value="-180" />
											<float name="y" value="0" />
											<float name="z" value="130" />
										</template_reference>
										<enum name="type" value="WorldPosition" />
									</group>
									<enum name="interpolation_type" value="Linear" />
								</template_reference>
							</list>
							<enum name="property" value="Translate" />
							<float name="repeat_count" value="0" />
						</template_reference>
					</list>
				</template_reference>
				<template_reference name="element" value="sitrep_data\element" List.ItemID="94862287">
					<string name="custom_label" value="Signals Vehicle 2 Cross" />
					<string name="type" value="Image" />
					<string name="style" value="ImageWithDropShadow" />
					<file name="image_path" value="icons\sitrep\enemy_cross" />
					<group name="dimension">
						<float name="width" value="100" />
						<float name="height" value="100" />
						<enum name="type" value="Pixels" />
					</group>
					<group name="position">
						<template_reference name="world_position" value="basic_data_types\vector3">
							<float name="x" value="120" />
							<float name="y" value="0" />
							<float name="z" value="20" />
						</template_reference>
						<enum name="type" value="WorldPosition" />
					</group>
					<list name="timeline">
						<template_reference name="animated_property" value="sitrep_data\animated_property" List.ItemID="1827228644">
							<list name="keyframes">
								<template_reference name="keyframe" value="sitrep_data\double_keyframe" List.ItemID="1107806370">
									<float name="key_time" value="0" />
									<float name="value" value="0" />
									<enum name="interpolation_type" value="Discrete" />
								</template_reference>
								<template_reference name="keyframe" value="sitrep_data\double_keyframe" List.ItemID="1017788329">
									<float name="key_time" value="13" />
									<float name="value" value="0" />
									<enum name="interpolation_type" value="Linear" />
								</template_reference>
								<template_reference name="keyframe" value="sitrep_data\double_keyframe" List.ItemID="1978213664">
									<float name="key_time" value="14" />
									<float name="value" value="1" />
									<enum name="interpolation_type" value="Linear" />
								</template_reference>
								<template_reference name="keyframe" value="sitrep_data\double_keyframe" List.ItemID="1785586289">
									<float name="key_time" value="16" />
									<float name="value" value="1" />
									<enum name="interpolation_type" value="Linear" />
								</template_reference>
								<template_reference name="keyframe" value="sitrep_data\double_keyframe" List.ItemID="433182103">
									<float name="key_time" value="17" />
									<float name="value" value="0" />
									<enum name="interpolation_type" value="Linear" />
								</template_reference>
							</list>
							<enum name="property" value="Opacity" />
							<float name="repeat_count" value="0" />
						</template_reference>
					</list>
				</template_reference>
				<template_reference name="element" value="sitrep_data\element" List.ItemID="1262434616">
					<string name="custom_label" value="Signals Vehicle 2 Revival" />
					<string name="type" value="Image" />
					<string name="style" value="ImageWithDropShadow" />
					<file name="image_path" value="icons\sitrep\friendly_chalk" />
					<group name="dimension">
						<float name="width" value="100" />
						<float name="height" value="100" />
						<enum name="type" value="Pixels" />
					</group>
					<group name="position">
						<template_reference name="world_position" value="basic_data_types\vector3">
							<float name="x" value="120" />
							<float name="y" value="0" />
							<float name="z" value="20" />
						</template_reference>
						<enum name="type" value="WorldPosition" />
					</group>
					<list name="timeline">
						<template_reference name="animated_property" value="sitrep_data\animated_property" List.ItemID="1597760940">
							<list name="keyframes">
								<template_reference name="keyframe" value="sitrep_data\double_keyframe" List.ItemID="547744636">
									<float name="key_time" value="0" />
									<float name="value" value="0" />
									<enum name="interpolation_type" value="Discrete" />
								</template_reference>
								<template_reference name="keyframe" value="sitrep_data\double_keyframe" List.ItemID="131032476">
									<float name="key_time" value="17" />
									<float name="value" value="0" />
									<enum name="interpolation_type" value="Linear" />
								</template_reference>
								<template_reference name="keyframe" value="sitrep_data\double_keyframe" List.ItemID="836286140">
									<float name="key_time" value="18" />
									<float name="value" value="1" />
									<enum name="interpolation_type" value="Linear" />
								</template_reference>
							</list>
							<enum name="property" value="Opacity" />
							<float name="repeat_count" value="0" />
						</template_reference>
						<template_reference name="animated_property" value="sitrep_data\animated_property" List.ItemID="360935661">
							<list name="keyframes">
								<template_reference name="keyframe" value="sitrep_data\position_keyframe" List.ItemID="236879144">
									<float name="key_time" value="0" />
									<group name="value">
										<template_reference name="world_position" value="basic_data_types\vector3">
											<float name="x" value="120" />
											<float name="y" value="0" />
											<float name="z" value="20" />
										</template_reference>
										<enum name="type" value="WorldPosition" />
									</group>
									<enum name="interpolation_type" value="Discrete" />
								</template_reference>
								<template_reference name="keyframe" value="sitrep_data\position_keyframe" List.ItemID="1459219659">
									<float name="key_time" value="35" />
									<group name="value">
										<template_reference name="world_position" value="basic_data_types\vector3">
											<float name="x" value="120" />
											<float name="y" value="0" />
											<float name="z" value="20" />
										</template_reference>
										<enum name="type" value="WorldPosition" />
									</group>
									<enum name="interpolation_type" value="Linear" />
								</template_reference>
								<template_reference name="keyframe" value="sitrep_data\position_keyframe" List.ItemID="168381619">
									<float name="key_time" value="38" />
									<group name="value">
										<template_reference name="world_position" value="basic_data_types\vector3">
											<float name="x" value="-180" />
											<float name="y" value="0" />
											<float name="z" value="130" />
										</template_reference>
										<enum name="type" value="WorldPosition" />
									</group>
									<enum name="interpolation_type" value="Linear" />
								</template_reference>
							</list>
							<enum name="property" value="Translate" />
							<float name="repeat_count" value="0" />
						</template_reference>
					</list>
				</template_reference>
				<template_reference name="element" value="sitrep_data\element" List.ItemID="1560766050">
					<string name="custom_label" value="Defense area 3" />
					<string name="type" value="Image" />
					<string name="style" value="ImageWithDropShadow" />
					<file name="image_path" value="icons\sitrep\friendly_alliedcross" />
					<group name="dimension">
						<float name="width" value="150" />
						<float name="height" value="150" />
						<enum name="type" value="Pixels" />
					</group>
					<group name="position">
						<template_reference name="world_position" value="basic_data_types\vector3">
							<float name="x" value="20" />
							<float name="y" value="0" />
							<float name="z" value="-180" />
						</template_reference>
						<enum name="type" value="WorldPosition" />
					</group>
					<list name="timeline">
					</list>
				</template_reference>
				<template_reference name="element" value="sitrep_data\element" List.ItemID="928107103">
					<string name="custom_label" value="Signals Vehicle 3" />
					<string name="type" value="Image" />
					<string name="style" value="ImageWithDropShadow" />
					<file name="image_path" value="icons\sitrep\primary_objective" />
					<group name="dimension">
						<float name="width" value="100" />
						<float name="height" value="100" />
						<enum name="type" value="Pixels" />
					</group>
					<group name="position">
						<template_reference name="world_position" value="basic_data_types\vector3">
							<float name="x" value="20" />
							<float name="y" value="0" />
							<float name="z" value="-160" />
						</template_reference>
						<enum name="type" value="WorldPosition" />
					</group>
					<list name="timeline">
						<template_reference name="animated_property" value="sitrep_data\animated_property" List.ItemID="1836706535">
							<list name="keyframes">
								<template_reference name="keyframe" value="sitrep_data\position_keyframe" List.ItemID="1093467948">
									<float name="key_time" value="0" />
									<group name="value">
										<template_reference name="world_position" value="basic_data_types\vector3">
											<float name="x" value="20" />
											<float name="y" value="0" />
											<float name="z" value="-160" />
										</template_reference>
										<enum name="type" value="WorldPosition" />
									</group>
									<enum name="interpolation_type" value="Discrete" />
								</template_reference>
								<template_reference name="keyframe" value="sitrep_data\position_keyframe" List.ItemID="1489332775">
									<float name="key_time" value="35" />
									<group name="value">
										<template_reference name="world_position" value="basic_data_types\vector3">
											<float name="x" value="20" />
											<float name="y" value="0" />
											<float name="z" value="-160" />
										</template_reference>
										<enum name="type" value="WorldPosition" />
									</group>
									<enum name="interpolation_type" value="Linear" />
								</template_reference>
								<template_reference name="keyframe" value="sitrep_data\position_keyframe" List.ItemID="422342915">
									<float name="key_time" value="38" />
									<group name="value">
										<template_reference name="world_position" value="basic_data_types\vector3">
											<float name="x" value="-180" />
											<float name="y" value="0" />
											<float name="z" value="130" />
										</template_reference>
										<enum name="type" value="WorldPosition" />
									</group>
									<enum name="interpolation_type" value="Linear" />
								</template_reference>
							</list>
							<enum name="property" value="Translate" />
							<float name="repeat_count" value="0" />
						</template_reference>
					</list>
				</template_reference>
				<template_reference name="element" value="sitrep_data\element" List.ItemID="1160347548">
					<string name="custom_label" value="Signals Vehicle 3 Cross" />
					<string name="type" value="Image" />
					<string name="style" value="ImageWithDropShadow" />
					<file name="image_path" value="icons\sitrep\enemy_cross" />
					<group name="dimension">
						<float name="width" value="100" />
						<float name="height" value="100" />
						<enum name="type" value="Pixels" />
					</group>
					<group name="position">
						<template_reference name="world_position" value="basic_data_types\vector3">
							<float name="x" value="20" />
							<float name="y" value="0" />
							<float name="z" value="-160" />
						</template_reference>
						<enum name="type" value="WorldPosition" />
					</group>
					<list name="timeline">
						<template_reference name="animated_property" value="sitrep_data\animated_property" List.ItemID="86311283">
							<list name="keyframes">
								<template_reference name="keyframe" value="sitrep_data\double_keyframe" List.ItemID="2008455174">
									<float name="key_time" value="0" />
									<float name="value" value="0" />
									<enum name="interpolation_type" value="Discrete" />
								</template_reference>
								<template_reference name="keyframe" value="sitrep_data\double_keyframe" List.ItemID="493100140">
									<float name="key_time" value="13" />
									<float name="value" value="0" />
									<enum name="interpolation_type" value="Linear" />
								</template_reference>
								<template_reference name="keyframe" value="sitrep_data\double_keyframe" List.ItemID="1266949348">
									<float name="key_time" value="14" />
									<float name="value" value="1" />
									<enum name="interpolation_type" value="Linear" />
								</template_reference>
								<template_reference name="keyframe" value="sitrep_data\double_keyframe" List.ItemID="625727772">
									<float name="key_time" value="16" />
									<float name="value" value="1" />
									<enum name="interpolation_type" value="Linear" />
								</template_reference>
								<template_reference name="keyframe" value="sitrep_data\double_keyframe" List.ItemID="260074286">
									<float name="key_time" value="17" />
									<float name="value" value="0" />
									<enum name="interpolation_type" value="Linear" />
								</template_reference>
							</list>
							<enum name="property" value="Opacity" />
							<float name="repeat_count" value="0" />
						</template_reference>
					</list>
				</template_reference>
				<template_reference name="element" value="sitrep_data\element" List.ItemID="1884858195">
					<string name="custom_label" value="Signals Vehicle 3 Revival" />
					<string name="type" value="Image" />
					<string name="style" value="ImageWithDropShadow" />
					<file name="image_path" value="icons\sitrep\friendly_chalk" />
					<group name="dimension">
						<float name="width" value="100" />
						<float name="height" value="100" />
						<enum name="type" value="Pixels" />
					</group>
					<group name="position">
						<template_reference name="world_position" value="basic_data_types\vector3">
							<float name="x" value="20" />
							<float name="y" value="0" />
							<float name="z" value="-160" />
						</template_reference>
						<enum name="type" value="WorldPosition" />
					</group>
					<list name="timeline">
						<template_reference name="animated_property" value="sitrep_data\animated_property" List.ItemID="72885329">
							<list name="keyframes">
								<template_reference name="keyframe" value="sitrep_data\double_keyframe" List.ItemID="148499528">
									<float name="key_time" value="0" />
									<float name="value" value="0" />
									<enum name="interpolation_type" value="Discrete" />
								</template_reference>
								<template_reference name="keyframe" value="sitrep_data\double_keyframe" List.ItemID="1028172729">
									<float name="key_time" value="17" />
									<float name="value" value="0" />
									<enum name="interpolation_type" value="Linear" />
								</template_reference>
								<template_reference name="keyframe" value="sitrep_data\double_keyframe" List.ItemID="1678963215">
									<float name="key_time" value="18" />
									<float name="value" value="1" />
									<enum name="interpolation_type" value="Linear" />
								</template_reference>
							</list>
							<enum name="property" value="Opacity" />
							<float name="repeat_count" value="0" />
						</template_reference>
						<template_reference name="animated_property" value="sitrep_data\animated_property" List.ItemID="1049945821">
							<list name="keyframes">
								<template_reference name="keyframe" value="sitrep_data\position_keyframe" List.ItemID="885493209">
									<float name="key_time" value="0" />
									<group name="value">
										<template_reference name="world_position" value="basic_data_types\vector3">
											<float name="x" value="20" />
											<float name="y" value="0" />
											<float name="z" value="-160" />
										</template_reference>
										<enum name="type" value="WorldPosition" />
									</group>
									<enum name="interpolation_type" value="Discrete" />
								</template_reference>
								<template_reference name="keyframe" value="sitrep_data\position_keyframe" List.ItemID="1342591032">
									<float name="key_time" value="35" />
									<group name="value">
										<template_reference name="world_position" value="basic_data_types\vector3">
											<float name="x" value="20" />
											<float name="y" value="0" />
											<float name="z" value="-160" />
										</template_reference>
										<enum name="type" value="WorldPosition" />
									</group>
									<enum name="interpolation_type" value="Linear" />
								</template_reference>
								<template_reference name="keyframe" value="sitrep_data\position_keyframe" List.ItemID="113163323">
									<float name="key_time" value="38" />
									<group name="value">
										<template_reference name="world_position" value="basic_data_types\vector3">
											<float name="x" value="-180" />
											<float name="y" value="0" />
											<float name="z" value="130" />
										</template_reference>
										<enum name="type" value="WorldPosition" />
									</group>
									<enum name="interpolation_type" value="Linear" />
								</template_reference>
							</list>
							<enum name="property" value="Translate" />
							<float name="repeat_count" value="0" />
						</template_reference>
					</list>
				</template_reference>
				<template_reference name="element" value="sitrep_data\element" List.ItemID="12084689">
					<string name="custom_label" value="Friendly Forward Barracks area" />
					<string name="type" value="Image" />
					<string name="style" value="ImageWithDropShadow" />
					<file name="image_path" value="icons\sitrep\friendly_hq" />
					<group name="dimension">
						<float name="width" value="100" />
						<float name="height" value="100" />
						<enum name="type" value="Pixels" />
					</group>
					<group name="position">
						<template_reference name="world_position" value="basic_data_types\vector3">
							<float name="x" value="-30" />
							<float name="y" value="0" />
							<float name="z" value="140" />
						</template_reference>
						<enum name="type" value="WorldPosition" />
					</group>
					<list name="timeline">
					</list>
				</template_reference>
				<template_reference name="element" value="sitrep_data\element" List.ItemID="406059412">
					<string name="custom_label" value="Invisible anchor object" />
					<string name="type" value="Ellipse" />
					<string name="style" value="BlackCircle" />
					<file name="image_path" value="" />
					<group name="dimension">
						<float name="width" value="0" />
						<float name="height" value="0" />
						<enum name="type" value="Pixels" />
					</group>
					<group name="position">
						<template_reference name="world_position" value="basic_data_types\vector3">
							<float name="x" value="0" />
							<float name="y" value="0" />
							<float name="z" value="0" />
						</template_reference>
						<enum name="type" value="WorldPosition" />
					</group>
					<list name="timeline">
						<template_reference name="animated_property" value="sitrep_data\animated_property" List.ItemID="1056116829">
							<list name="keyframes">
								<template_reference name="keyframe" value="sitrep_data\double_keyframe" List.ItemID="2121834373">
									<float name="key_time" value="0" />
									<float name="value" value="0" />
									<enum name="interpolation_type" value="Discrete" />
								</template_reference>
								<template_reference name="keyframe" value="sitrep_data\double_keyframe" List.ItemID="734682111">
									<float name="key_time" value="40" />
									<float name="value" value="0" />
									<enum name="interpolation_type" value="Linear" />
								</template_reference>
							</list>
							<enum name="property" value="Opacity" />
							<float name="repeat_count" value="0" />
						</template_reference>
					</list>
				</template_reference>
			</list>
			<file name="map_image_path" value="missions\africa\archetype\hold\desert_route_hold_tm_handmade" />
			<float name="playable_width" value="512" />
			<float name="playable_height" value="512" />
			<file name="narrative_collection" value="it_sitreps_narrative" />
			<string name="narrative_event" value="desert_route_hold_sitrep" />
			<int name="narrative_variant" value="0" />
		</group>
	</variant>
</instance>