<instance version="5" description="" template="attachments\customizations\anvil_attachment_customization_damage">
	<variant name="default">
		<group name="anvil_attachment_customization_damage">
			<file name="damage_material" value="art\armies\common\procedural\damage\dmg_ballistic_dense_lrg" />
			<float name="damage_uv_offset_u" value="0" />
			<float name="damage_uv_offset_v" value="0" />
			<float name="damage_uv_scale_u" value="1" />
			<float name="damage_uv_scale_v" value="1" />
		</group>
		<uniqueid name="pbgid" value="2063223" />
	</variant>
</instance>