<instance version="5" description="" template="attachments\attachment_list">
	<variant name="default">
		<group name="attachment_list_group">
			<list name="attachment_list">
				<template_reference name="attachment" value="options\attachment_types\animator_skin_attachment" List.ItemID="-358457876">
					<file name="animator" value="art\armies\dak\vehicles\panzer3\body\chassis\chassis" />
					<enum name="inventory_item_category" value="default" />
					<bool name="is_selectable" value="True" />
					<string name="marker_name" value="" />
					<file name="material_override" value="" />
					<list name="customizations">
						<instance_reference name="customization" value="attachments\customizations\anvil_attachment_customization_tint\dak_tint_ral_7008" List.ItemID="-1009322932" />
						<instance_reference name="customization" value="attachments\customizations\anvil_attachment_customization_decal\vehicles\dak\dak_panzer_3_decal_set" List.ItemID="484003515" />
						<instance_reference name="customization" value="attachments\customizations\anvil_attachment_customization_charred\charring_damage" List.ItemID="1827867489" />
						<instance_reference name="customization" value="attachments\customizations\anvil_attachment_customization_weathering\mud_dry" List.ItemID="619272427" />
						<instance_reference name="customization" value="attachments\customizations\anvil_attachment_customization_damage\ballistic_gritty_01_damage" List.ItemID="363673493" />
					</list>
				</template_reference>
				<template_reference name="attachment" value="options\attachment_types\animator_skin_attachment" List.ItemID="-1322614969">
					<file name="animator" value="art\armies\dak\vehicles\panzer3\body\armor\armor" />
					<enum name="inventory_item_category" value="" />
					<bool name="is_selectable" value="True" />
					<string name="marker_name" value="" />
					<file name="material_override" value="" />
					<list name="customizations">
						<instance_reference name="customization" value="attachments\customizations\anvil_attachment_customization_tint\dak_tint_ral_7008" List.ItemID="2000921558" />
						<instance_reference name="customization" value="attachments\customizations\anvil_attachment_customization_decal\vehicles\dak\dak_panzer_3_decal_set" List.ItemID="1216255014" />
						<instance_reference name="customization" value="attachments\customizations\anvil_attachment_customization_charred\charring_damage" List.ItemID="-332207942" />
						<instance_reference name="customization" value="attachments\customizations\anvil_attachment_customization_weathering\mud_dry" List.ItemID="-316643811" />
						<instance_reference name="customization" value="attachments\customizations\anvil_attachment_customization_damage\ballistic_gritty_01_damage" List.ItemID="1557604253" />
					</list>
				</template_reference>
			</list>
			<string name="attachment_category" value="side_skirts" />
			<string name="attachment_speaker_code" value="" />
			<string name="inventory_category" value="side_skirts" />
		</group>
		<uniqueid name="pbgid" value="1512420" />
		<instance_reference name="parent_pbg" value="" />
	</variant>
</instance>