<instance version="5" description="" template="attachments\attachment_lists">
	<variant name="default">
		<group name="attachment_lists_group">
			<list name="attachment_lists">
				<instance_reference name="attachment_lists_option" value="attachments\attachment_list\gameplay\strategic_points\territory_victory_point_flag\territory_victory_point_flag_uk" List.ItemID="753011353" />
			</list>
			<file name="parent_animator" value="art\gameplay\rigs\capture_point_flag\capture_point_flag" />
			<file name="parent_material_override" value="" />
			<list name="parent_customizations">
			</list>
		</group>
		<uniqueid name="pbgid" value="1526099" />
		<instance_reference name="parent_pbg" value="" />
	</variant>
</instance>